pynewton/__init__.py
pynewton/extensions.py
pynewton/extensions.pyi
pynewton/wrapper.py
pynewton-1.1.2.dist-info/WHEEL
pynewton-1.1.2.dist-info/METADATA
pynewton-1.1.2.dist-info/RECORD
