Metadata-Version: 2.1
Name: pynewton
Version: 1.1.2
Summary: An asyncio-based wrapper for the newton-api
Home-page: https://github.com/HitaloSama/pynewton
License: MIT
Author: Nils Theres
Requires-Python: >=3.6,<4.0
Classifier: License :: OSI Approved :: MIT License
Classifier: Programming Language :: Python :: 3
Classifier: Programming Language :: Python :: 3.6
Classifier: Programming Language :: Python :: 3.7
Classifier: Programming Language :: Python :: 3.8
Classifier: Programming Language :: Python :: 3.9
Requires-Dist: httpx[http2] (>=0.17.1,<0.18.0)
Project-URL: Repository, https://github.com/HitaloSama/pynewton
